fw_gear_splitter/__init__.py
fw_gear_splitter/geometry.py
fw_gear_splitter/main.py
fw_gear_splitter/metadata.py
fw_gear_splitter/parser.py
fw_gear_splitter/splitter/__init__.py
fw_gear_splitter/splitter/base.py
fw_gear_splitter/splitters.py
fw_gear_splitter/utils.py
fw_gear_splitter-1.7.2.dist-info/LICENSE
fw_gear_splitter-1.7.2.dist-info/METADATA
fw_gear_splitter-1.7.2.dist-info/WHEEL
fw_gear_splitter-1.7.2.dist-info/RECORD
