Metadata-Version: 2.1
Name: fw-gear-splitter
Version: 1.7.2
Summary: DICOM splitter based on unique tags, or localizers
License: MIT
Author: Flywheel
Author-email: support@flywheel.io
Requires-Python: >=3.8,<4
Classifier: License :: OSI Approved :: MIT License
Classifier: Programming Language :: Python :: 3
Classifier: Programming Language :: Python :: 3.8
Classifier: Programming Language :: Python :: 3.9
Classifier: Programming Language :: Python :: 3.10
Classifier: Programming Language :: Python :: 3.11
Classifier: Programming Language :: Python :: 3.12
Requires-Dist: flywheel-gear-toolkit (>=0.6.18,<0.7.0)
Requires-Dist: flywheel-sdk (>=16.0.0,<17.0.0)
Requires-Dist: fw-file (>=3,<4)
Requires-Dist: pandas (>=1.2.1,<2.0.0)
Requires-Dist: pylibjpeg (>=1.1.1,<2.0.0)
Requires-Dist: pylibjpeg-libjpeg (>=1.1.0,<2.0.0)
Requires-Dist: pylibjpeg-openjpeg (>=1.0.1,<2.0.0)
Requires-Dist: scipy (>=1.8.0,<2.0.0)
